setup.cfg
setup.py
./_cracklib.c
./cracklib.py
./test_cracklib.py
cracklib.egg-info/PKG-INFO
cracklib.egg-info/SOURCES.txt
cracklib.egg-info/dependency_links.txt
cracklib.egg-info/not-zip-safe
cracklib.egg-info/top_level.txt