Metadata-Version: 2.1
Name: cracklib
Version: 2.9.6
Summary: A CPython extension module wrapping the libcrack library
Home-page: http://cracklib.sourceforge.net/
Author: Jan Dittberner
Author-email: jan@dittberner.info
License: GPLv2+
Classifier: Development Status :: 4 - Beta
Classifier: Intended Audience :: Developers
Classifier: License :: OSI Approved :: GNU Library or Lesser General Public License (LGPL)
Classifier: Operating System :: OS Independent
Classifier: Programming Language :: Python
Classifier: Topic :: Security
Classifier: Topic :: Software Development :: Libraries :: Python Modules
Classifier: Topic :: System :: Systems Administration
